dsenum-0.4.4.dist-info/LICENSE
dsenum-0.4.4.dist-info/METADATA
dsenum-0.4.4.dist-info/RECORD
dsenum-0.4.4.dist-info/top_level.txt
dsenum-0.4.4.dist-info/WHEEL
dsenum/polya.py
dsenum/site.py
dsenum/py.typed
dsenum/coloring.py
dsenum/superlattice.py
dsenum/core.cpython-310-x86_64-linux-gnu.so
dsenum/enumerate.py
dsenum/coloring_generator.py
dsenum/core.c
dsenum/permutation_group.py
dsenum/__init__.py
dsenum/core.pyx
dsenum/utils.py
dsenum/derivative_structure.py
dsenum/converter.py
dsenum/_version.py
dsenum/cluster/__init__.py
dsenum/cluster/point_cluster.py
