Metadata-Version: 2.1
Name: dsenum
Version: 0.4.4
Summary: Derivative structure enumerator for multilattice
Author: Kohei Shinohara
Author-email: kohei19950508@gmail.com
License: MIT
Classifier: Development Status :: 2 - Pre-Alpha
Classifier: Intended Audience :: Science/Research
Classifier: License :: OSI Approved :: MIT License
Classifier: Operating System :: POSIX :: Linux
Classifier: Programming Language :: Python
Classifier: Programming Language :: Python :: 3.8
Classifier: Programming Language :: Python :: 3.9
Classifier: Programming Language :: Python :: 3.10
Classifier: Programming Language :: Python :: 3.11
Classifier: Programming Language :: Python :: Implementation :: CPython
Classifier: Topic :: Scientific/Engineering :: Chemistry
Classifier: Topic :: Scientific/Engineering :: Physics
Requires-Python: >=3.8
License-File: LICENSE
Requires-Dist: setuptools
Requires-Dist: setuptools-scm
Requires-Dist: wheel
Requires-Dist: pymatgen >2022.11.7
Requires-Dist: numpy
Requires-Dist: sympy
Requires-Dist: scipy
Requires-Dist: tqdm
Requires-Dist: hsnf >=0.3.15
Requires-Dist: pyzdd
Provides-Extra: dev
Requires-Dist: ipython ; extra == 'dev'
Requires-Dist: notebook ; extra == 'dev'
Requires-Dist: jupyter-contrib-nbextensions ; extra == 'dev'
Requires-Dist: matplotlib ; extra == 'dev'
Requires-Dist: seaborn ; extra == 'dev'
Requires-Dist: pandas ; extra == 'dev'
Requires-Dist: pytest >=6.0.0 ; extra == 'dev'
Requires-Dist: pytest-cov ; extra == 'dev'
Requires-Dist: pytest-benchmark ; extra == 'dev'
Requires-Dist: pre-commit ; extra == 'dev'
Requires-Dist: black ; extra == 'dev'
Requires-Dist: flake8 ; extra == 'dev'
Requires-Dist: mypy ; extra == 'dev'
Requires-Dist: isort ; extra == 'dev'
Requires-Dist: pyupgrade ; extra == 'dev'
Provides-Extra: docs
Requires-Dist: sphinx ; extra == 'docs'
Requires-Dist: sphinx-autobuild ; extra == 'docs'
Requires-Dist: nbsphinx ==0.9.3 ; extra == 'docs'
Requires-Dist: myst-parser ; extra == 'docs'
Requires-Dist: sphinx-book-theme ; extra == 'docs'
Requires-Dist: ipykernel ; extra == 'docs'
